tweet_archiveur/__init__.py
tweet_archiveur/_nbdev.py
tweet_archiveur/database.py
tweet_archiveur/scrapper.py
tweet_archiveur-0.0.1.dist-info/LICENSE
tweet_archiveur-0.0.1.dist-info/METADATA
tweet_archiveur-0.0.1.dist-info/WHEEL
tweet_archiveur-0.0.1.dist-info/entry_points.txt
tweet_archiveur-0.0.1.dist-info/top_level.txt
tweet_archiveur-0.0.1.dist-info/RECORD
