Metadata-Version: 2.1
Name: tweet-archiveur
Version: 0.0.1
Summary: Script to store tweets of a list of users in a databases for NLP processing.
Home-page: https://github.com/leximpact/tweet-archiveur/tree/main/
Author: benoit-cty
Author-email: anne@onymous.fr
License: Apache Software License 2.0
Keywords: tweet twitter parliement
Platform: UNKNOWN
Classifier: Development Status :: 3 - Alpha
Classifier: Intended Audience :: Developers
Classifier: Natural Language :: English
Classifier: Programming Language :: Python :: 3.6
Classifier: Programming Language :: Python :: 3.7
Classifier: Programming Language :: Python :: 3.8
Classifier: License :: OSI Approved :: Apache Software License
Requires-Python: >=3.6
